sequence_analyzer/__init__.py
sequence_analyzer/analyzer.py
sequence_analyzer-0.1.0.dist-info/LICENSE
sequence_analyzer-0.1.0.dist-info/METADATA
sequence_analyzer-0.1.0.dist-info/WHEEL
sequence_analyzer-0.1.0.dist-info/top_level.txt
sequence_analyzer-0.1.0.dist-info/RECORD
