Metadata-Version: 2.2
Name: sequence_analyzer
Version: 0.1.0
Summary: A simple DNA sequence analysis package
Home-page: https://github.com/yourusername/sequence_analyzer
Author: Your Name
Author-email: your-email@example.com
Classifier: Programming Language :: Python :: 3
Classifier: License :: OSI Approved :: MIT License
Classifier: Operating System :: OS Independent
Requires-Python: >=3.6
License-File: LICENSE
Requires-Dist: biopython
Requires-Dist: matplotlib
Dynamic: author
Dynamic: author-email
Dynamic: classifier
Dynamic: description-content-type
Dynamic: home-page
Dynamic: requires-dist
Dynamic: requires-python
Dynamic: summary
